anydbconnect/__init__.py
anydbconnect/mongodb_crud.py
anydbconnect-0.0.5.dist-info/LICENSE
anydbconnect-0.0.5.dist-info/METADATA
anydbconnect-0.0.5.dist-info/WHEEL
anydbconnect-0.0.5.dist-info/top_level.txt
anydbconnect-0.0.5.dist-info/RECORD
